stix_shifter_modules/abuseipdb/__init__.py
stix_shifter_modules/abuseipdb/entry_point.py
stix_shifter_modules/abuseipdb/configuration/config.json
stix_shifter_modules/abuseipdb/configuration/dialects.json
stix_shifter_modules/abuseipdb/configuration/lang_en.json
stix_shifter_modules/abuseipdb/stix_translation/__init__.py
stix_shifter_modules/abuseipdb/stix_translation/json_to_stix_translator.py
stix_shifter_modules/abuseipdb/stix_translation/query_constructor.py
stix_shifter_modules/abuseipdb/stix_translation/query_translator.py
stix_shifter_modules/abuseipdb/stix_translation/results_translator.py
stix_shifter_modules/abuseipdb/stix_translation/sdo_translator.py
stix_shifter_modules/abuseipdb/stix_translation/json/from_stix_map.json
stix_shifter_modules/abuseipdb/stix_translation/json/operators.json
stix_shifter_modules/abuseipdb/stix_translation/json/to_stix_map.json
stix_shifter_modules/abuseipdb/stix_transmission/__init__.py
stix_shifter_modules/abuseipdb/stix_transmission/api_client.py
stix_shifter_modules/abuseipdb/stix_transmission/delete_connector.py
stix_shifter_modules/abuseipdb/stix_transmission/error_mapper.py
stix_shifter_modules/abuseipdb/stix_transmission/ping_connector.py
stix_shifter_modules/abuseipdb/stix_transmission/results_connector.py
stix_shifter_modules_abuseipdb-5.3.1.dist-info/LICENSE.md
stix_shifter_modules_abuseipdb-5.3.1.dist-info/METADATA
stix_shifter_modules_abuseipdb-5.3.1.dist-info/NOTICE
stix_shifter_modules_abuseipdb-5.3.1.dist-info/WHEEL
stix_shifter_modules_abuseipdb-5.3.1.dist-info/top_level.txt
stix_shifter_modules_abuseipdb-5.3.1.dist-info/RECORD
